{
    "one": [
        {
            "id": 0,
            "name": "Long Shot",
            "email": "Plano Aberto",
            "picture": "longshot.jpg",
            "description": "(a) PLANO ABERTO (“LONG SHOT”) – a câmera está distante do objeto, de modo que ele ocupa uma parte pequena do cenário. É um plano de AMBIENTAÇÃO."
        },
        {
            "id": 1,
            "name": "Medium Shot",
            "email": "Plano Médio",
            "picture": "mediumshot.jpg",
            "description": "(b) PLANO MÉDIO (“MEDIUM SHOT”) – a câmera está a uma distância média do objeto, de modo que ele ocupa uma parte considerável do ambiente, mas ainda tem espaço à sua volta. É um plano de POSICIONAMENTO e MOVIMENTAÇÃO."
        },
        {
            "id": 2,
            "name": "Close Up",
            "email": "Plano Fechado",
            "picture": "closeup.jpg",
            "description": "(c) PLANO FECHADO (“CLOSE-UP) – a câmera está bem próxima do objeto, de modo que ele ocupa quase todo o cenário, sem deixar grandes espaços à sua volta. É um plano de INTIMIDADE e EXPRESSÃO."
        },
        {
            "id": 3,
            "name": "(PG) Plano Geral",
            "email": "Plano Geral",
            "picture": "pg.jpg",
            "description": "(a) PLANO GERAL (PG) – Com um ângulo visual bem aberto, a câmera revela o cenário à sua frente. A figura humana ocupa espaço muito reduzido na tela. Plano para exteriores ou interiores de grandes proporções. Também chamado, na intimidade, de “Geralzão”."
        },
        {
            "id": 4,
            "name": "(PC) Plano de Conjunto",
            "email": "Plano Conjunto",
            "picture": "pc.jpg",
            "description": "(b) PLANO DE CONJUNTO (PC) – Com um ângulo visual aberto, a câmera revela uma parte significativa do cenário à sua frente. A figura humana ocupa um espaço relativamente maior na tela. É possível reconhecer os rostos das pessoas mais próximas à câmera. Também poderíamos chamá-lo de “Geralzinho”."
        },
        {
            "id": 5,
            "name": "(PM) Plano Médio",
            "email": "Plano Médio",
            "picture": "pm.jpg",
            "description": "(c) PLANO MÉDIO (PM) – A figura humana é enquadrada por inteiro, com um pouco de “ar” sobre a cabeça e um pouco de “chão” sob os pés."
        },
        {
            "id": 6,
            "name": "(PA) Plano Americano",
            "email": "Plano Americano",
            "picture": "pa.jpg",
            "description": "(d) PLANO AMERICANO (PA) – A figura humana é enquadrada do joelho para cima."
        },
        {
            "id": 7,
            "name": "(MPP) Meio Primeiro Plano",
            "email": "Meio Primeiro Plano",
            "picture": "mpp.jpg",
            "description": "(e) MEIO PRIMEIRO PLANO (MPP) – A figura humana é enquadrada da cintura para cima."
        }
    ],
    "two": [
        {
            "id": 0,
            "name": "Avatar 1",
            "email": "avatar1@gmail.com",
            "picture": "1.jpg"
        },
        {
            "id": 1,
            "name": "Avatar 2",
            "email": "'avatar2@gmail.com'",
            "picture": "3.png"
        },
        {
            "id": 2,
            "name": "Avatar 3",
            "email": "'avatar3@gmail.com'",
            "picture": "4.jpeg"
        }
    ],
    "three": [
        {
            "id": 0,
            "name": "Avatar 1",
            "email": "avatar1@gmail.com",
            "picture": "2.png"
        },
        {
            "id": 1,
            "name": "Avatar 2",
            "email": "'avatar2@gmail.com'",
            "picture": "3.png"
        },
        {
            "id": 2,
            "name": "Avatar 3",
            "email": "'avatar3@gmail.com'",
            "picture": "4.jpeg"
        },
        {
            "id": 3,
            "name": "Avatar 3",
            "email": "'avatar3@gmail.com'",
            "picture": "4.jpeg"
        },
        {
            "id": 4,
            "name": "Avatar 3",
            "email": "'avatar3@gmail.com'",
            "picture": "4.jpeg"
        }
    ]
}